LICENSE
MANIFEST.in
README.rst
requirements.txt
setup.cfg
setup.py
auto_graph_visualizer/__init__.py
auto_graph_visualizer/arg_parser.py
auto_graph_visualizer/compatibility.py
auto_graph_visualizer/core.py
auto_graph_visualizer/cy_visual.json
auto_graph_visualizer/resource_manager.py
auto_graph_visualizer/tmp.py
auto_graph_visualizer/utils.py
auto_graph_visualizer/visualizer.py
auto_graph_visualizer.egg-info/PKG-INFO
auto_graph_visualizer.egg-info/SOURCES.txt
auto_graph_visualizer.egg-info/dependency_links.txt
auto_graph_visualizer.egg-info/entry_points.txt
auto_graph_visualizer.egg-info/requires.txt
auto_graph_visualizer.egg-info/top_level.txt