Metadata-Version: 1.1
Name: auto-graph-visualizer
Version: 0.1.1
Summary: Automatic graph visualization package
Home-page: https://github.com/idekerlab/auto-graph-visualizer
Author: Mikio Shiga, Atsuya Matsubara
Author-email: m-shiga@ist.osaka-u.ac.jp, at-matbr@ist.osaka-u.ac.jp
License: UNKNOWN
Platform: UNKNOWN
Classifier: Development Status :: 3 - Alpha
Classifier: Intended Audience :: Developers
Classifier: Natural Language :: English
Classifier: License :: OSI Approved :: MIT License
Classifier: Programming Language :: Python :: 3
Classifier: Programming Language :: Python :: 3.7
Classifier: Programming Language :: Python :: Implementation :: CPython
Classifier: Programming Language :: Python :: Implementation :: PyPy
